argumentize/__init__.py
argumentize-1.0.4.dist-info/LICENSE.md
argumentize-1.0.4.dist-info/METADATA
argumentize-1.0.4.dist-info/WHEEL
argumentize-1.0.4.dist-info/top_level.txt
argumentize-1.0.4.dist-info/RECORD
