Metadata-Version: 2.1
Name: argumentize
Version: 1.0.4
Summary: Simple library for patching function inner scope 
Home-page: UNKNOWN
Author: liubomyr.ivanitskyi
Author-email: lubomyr.ivanitskiy@gmail.com
License: MIT License
Platform: UNKNOWN
License-File: LICENSE.md
